pgwidget/__init__.py
pgwidget/engine.py
pgwidget/helper.py
pgwidget/pgwidget_core.py
pgwidget-0.8.1.dist-info/LICENSE
pgwidget-0.8.1.dist-info/METADATA
pgwidget-0.8.1.dist-info/WHEEL
pgwidget-0.8.1.dist-info/top_level.txt
pgwidget-0.8.1.dist-info/RECORD
