Metadata-Version: 2.1
Name: pgwidget
Version: 0.8.1
Summary: Widgets for pygame
Home-page: https://github.com/DovaX/pgwidget
Author: DovaX
Author-email: dovax.ai@gmail.com
Classifier: Programming Language :: Python :: 3
Classifier: License :: OSI Approved :: MIT License
Classifier: Operating System :: OS Independent
Requires-Python: >=3.6
License-File: LICENSE
Requires-Dist: pygame
Requires-Dist: pandas
Requires-Dist: multinherit
Requires-Dist: doxyplot
Requires-Dist: remi
